xportr/__init__.py
xportr/cardinal.py
xportr/cardinal_sampler_builder.py
xportr/model.py
xportr/pool.py
xportr/requirements.py
xportr/sampler.py
xportr/timestamped_deque.py
xportr/utils.py
xportr/prometheus/__init__.py
xportr/prometheus/formatter.py
xportr-0.0.6.dist-info/LICENSE
xportr-0.0.6.dist-info/METADATA
xportr-0.0.6.dist-info/WHEEL
xportr-0.0.6.dist-info/top_level.txt
xportr-0.0.6.dist-info/RECORD
