Metadata-Version: 2.1
Name: xportr
Version: 0.0.6
Summary: Lightweight Prometheus exporter
Home-page: https://github.com/olivernadj/xportr
Author: Oliver Nadj
Author-email: mr.oliver.nadj@gmail.com
License: MIT
Platform: UNKNOWN
Classifier: License :: OSI Approved :: MIT License
Classifier: Programming Language :: Python :: 3.10
Classifier: Operating System :: OS Independent
Classifier: Topic :: System :: Monitoring
Requires-Python: >=3.10
License-File: LICENSE
Provides-Extra: dev
Requires-Dist: pytest-cov >=4.1.0 ; extra == 'dev'
Requires-Dist: pytest >=8.0.2 ; extra == 'dev'
Requires-Dist: ruff ==0.3.2 ; extra == 'dev'
Requires-Dist: twine >=4.0.2 ; extra == 'dev'
